ipvanishproxy/__init__.py
ipvanishproxy/proxy.py
ipvanishproxy-1.0.2.dist-info/METADATA
ipvanishproxy-1.0.2.dist-info/WHEEL
ipvanishproxy-1.0.2.dist-info/top_level.txt
ipvanishproxy-1.0.2.dist-info/RECORD
