Metadata-Version: 2.1
Name: ipvanishproxy
Version: 1.0.2
Summary: ipVanish proxy dictionary package
Author: Nahom Dereje
Author-email: dev@nahom.eu.org
Keywords: IpVanish,Proxy
Classifier: Development Status :: 3 - Alpha
Classifier: Intended Audience :: Education
Classifier: Programming Language :: Python :: 3
Classifier: Operating System :: MacOS :: MacOS X
Classifier: Operating System :: Microsoft :: Windows
